setup.py
Serializer_XML_And_JSON_Uladzislau.egg-info/PKG-INFO
Serializer_XML_And_JSON_Uladzislau.egg-info/SOURCES.txt
Serializer_XML_And_JSON_Uladzislau.egg-info/dependency_links.txt
Serializer_XML_And_JSON_Uladzislau.egg-info/top_level.txt
serializers/src/__init__.py
serializers/src/constants.py
serializers/src/converter.py
serializers/src/factory.py
serializers/src/json_serializer.py
serializers/src/supportive.py
serializers/src/xml_serializer.py